metorial_openai_compatible/__init__.py
metorial_openai_compatible/metorial_openai_compatible.py
metorial_openai_compatible-1.0.5.dist-info/METADATA
metorial_openai_compatible-1.0.5.dist-info/WHEEL
metorial_openai_compatible-1.0.5.dist-info/licenses/LICENSE
metorial_openai_compatible-1.0.5.dist-info/RECORD
