Metadata-Version: 2.4
Name: metorial-openai-compatible
Version: 1.0.5
Summary: OpenAI-compatible provider base for Metorial
Project-URL: Homepage, https://metorial.com
Project-URL: Documentation, https://metorial.com/docs
Project-URL: Repository, https://github.com/metorial/metorial-python
Author-email: Metorial Team <support@metorial.com>
License: MIT
License-File: LICENSE
Keywords: ai,compatible,llm,metorial,openai
Classifier: Development Status :: 4 - Beta
Classifier: Intended Audience :: Developers
Classifier: Programming Language :: Python :: 3
Classifier: Programming Language :: Python :: 3.10
Classifier: Programming Language :: Python :: 3.11
Classifier: Programming Language :: Python :: 3.12
Classifier: Topic :: Scientific/Engineering :: Artificial Intelligence
Classifier: Topic :: Software Development :: Libraries :: Python Modules
Requires-Python: >=3.10
Requires-Dist: metorial-core>=1.0.9
Requires-Dist: typing-extensions>=4.0.0
